convMD/__init__.py
convMD/md_into_html.py
convMD/md_lexing.py
convMD-0.0.1.dist-info/LICENSE
convMD-0.0.1.dist-info/METADATA
convMD-0.0.1.dist-info/WHEEL
convMD-0.0.1.dist-info/top_level.txt
convMD-0.0.1.dist-info/RECORD
